pyrade/__init__.py
pyrade/__version__.py
pyrade/experiments.py
pyrade/runner.py
pyrade/visualization.py
pyrade/algorithms/README.md
pyrade/algorithms/__init__.py
pyrade/algorithms/adaptive/__init__.py
pyrade/algorithms/adaptive/apsde.py
pyrade/algorithms/adaptive/jade.py
pyrade/algorithms/adaptive/jde.py
pyrade/algorithms/adaptive/jso.py
pyrade/algorithms/adaptive/lshade.py
pyrade/algorithms/adaptive/lshade_epsin.py
pyrade/algorithms/adaptive/sade.py
pyrade/algorithms/adaptive/shade.py
pyrade/algorithms/classic/__init__.py
pyrade/algorithms/hybrid/__init__.py
pyrade/algorithms/multi_population/__init__.py
pyrade/benchmarks/.gitkeep
pyrade/benchmarks/CEC2022_README.md
pyrade/benchmarks/__init__.py
pyrade/benchmarks/cec2017.py
pyrade/benchmarks/cec2022.py
pyrade/benchmarks/functions.py
pyrade/core/.gitkeep
pyrade/core/__init__.py
pyrade/core/algorithm.py
pyrade/core/population.py
pyrade/operators/.gitkeep
pyrade/operators/__init__.py
pyrade/operators/crossover.py
pyrade/operators/mutation.py
pyrade/operators/selection.py
pyrade/utils/.gitkeep
pyrade/utils/__init__.py
pyrade/utils/adaptation.py
pyrade/utils/boundary.py
pyrade/utils/chaotic.py
pyrade/utils/opposition.py
pyrade/utils/termination.py
pyrade-0.4.4.dist-info/licenses/LICENSE
pyrade-0.4.4.dist-info/METADATA
pyrade-0.4.4.dist-info/WHEEL
pyrade-0.4.4.dist-info/top_level.txt
pyrade-0.4.4.dist-info/RECORD
