Metadata-Version: 2.4
Name: pyrade
Version: 0.4.4
Summary: High-performance, modular Differential Evolution optimization
Home-page: https://github.com/arartawil/pyrade
Author: PyRADE Contributors
Author-email: PyRADE Contributors <arartawil@gmail.com>
License: MIT
Project-URL: Homepage, https://github.com/arartawil/pyrade
Project-URL: Documentation, https://github.com/arartawil/pyrade/blob/main/API_DOCUMENTATION.md
Project-URL: Repository, https://github.com/arartawil/pyrade
Project-URL: Bug Reports, https://github.com/arartawil/pyrade/issues
Keywords: optimization,differential evolution,evolutionary algorithms,metaheuristics
Classifier: Development Status :: 4 - Beta
Classifier: Intended Audience :: Science/Research
Classifier: Intended Audience :: Developers
Classifier: Topic :: Scientific/Engineering
Classifier: Topic :: Scientific/Engineering :: Artificial Intelligence
Classifier: Topic :: Scientific/Engineering :: Mathematics
Classifier: License :: OSI Approved :: MIT License
Classifier: Programming Language :: Python :: 3
Classifier: Programming Language :: Python :: 3.7
Classifier: Programming Language :: Python :: 3.8
Classifier: Programming Language :: Python :: 3.9
Classifier: Programming Language :: Python :: 3.10
Classifier: Programming Language :: Python :: 3.11
Classifier: Programming Language :: Python :: 3.12
Requires-Python: >=3.7
License-File: LICENSE
Requires-Dist: numpy>=1.20.0
Requires-Dist: tqdm>=4.65.0
Provides-Extra: dev
Requires-Dist: pytest>=6.0; extra == "dev"
Requires-Dist: pytest-cov>=2.0; extra == "dev"
Requires-Dist: black>=21.0; extra == "dev"
Requires-Dist: flake8>=3.9; extra == "dev"
Requires-Dist: mypy>=0.910; extra == "dev"
Dynamic: author
Dynamic: home-page
Dynamic: license-file
Dynamic: requires-python
